arcade_notion/__init__.py
arcade_notion/markdown_processor.py
arcade_notion/notion_api.py
arcade_notion/services.py
arcade_notion/tools/__init__.py
arcade_notion/tools/create_page_by_title.py
arcade_notion/tools/create_subpage.py
arcade_notion/tools/get_page_id.py
arcade_notion/types.py
arcade_notion-0.1.1.dist-info/LICENCE
arcade_notion-0.1.1.dist-info/METADATA
arcade_notion-0.1.1.dist-info/WHEEL
arcade_notion-0.1.1.dist-info/RECORD
