Metadata-Version: 2.1
Name: arcade_notion
Version: 0.1.1
Summary: Notion integration to search, create, update, and delete databases/pages.
Author: Sergio Serrano
Author-email: sdserranog@gmail.com
Requires-Python: >=3.10,<4.0
Classifier: Programming Language :: Python :: 3
Classifier: Programming Language :: Python :: 3.10
Classifier: Programming Language :: Python :: 3.11
Classifier: Programming Language :: Python :: 3.12
Classifier: Programming Language :: Python :: 3.13
Requires-Dist: arcade-ai (>=0.1.1,<0.2.0)
Requires-Dist: loguru (>=0.7.0,<0.8.0)
Requires-Dist: requests (>=2.31.0,<3.0.0)
